Metadata-Version: 1.2
Name: moneylib
Version: 0.1.1
Summary: Python library for easy deal with money and currencies. The main point is that any operations with money will be processed with the amount in the particular currency.
